README.md
setup.py
pycassos/__init__.py
pycassos/__main__.py
pycassos.egg-info/PKG-INFO
pycassos.egg-info/SOURCES.txt
pycassos.egg-info/dependency_links.txt
pycassos.egg-info/entry_points.txt
pycassos.egg-info/not-zip-safe
pycassos.egg-info/requires.txt
pycassos.egg-info/top_level.txt